{
  "variants": {
    "facing=north": [
      {  "model": "rw_block_mod:block/sheetbox_su_0", "y": 0},
      {  "model": "rw_block_mod:block/sheetbox_su_1", "y": 0}
    ],

    "facing=south": [
      {  "model": "rw_block_mod:block/sheetbox_su_0", "y": 180},
      {  "model": "rw_block_mod:block/sheetbox_su_1", "y": 180}
    ],

    "facing=east": [
      {  "model": "rw_block_mod:block/sheetbox_su_0", "y": 90},
      {  "model": "rw_block_mod:block/sheetbox_su_1", "y": 90}
    ],

    "facing=west": [
      {  "model": "rw_block_mod:block/sheetbox_su_0", "y": 270},
      {  "model": "rw_block_mod:block/sheetbox_su_1", "y": 270}
    ]


  }
}